{
    "key": "group_62d2e784558d9",
    "title": "Letter of the Day",
    "fields": [
        {
            "key": "field_62d52d7229e2a",
            "label": "<b>Link<\/b>",
            "name": "",
            "type": "message",
            "instructions": "",
            "required": 0,
            "conditional_logic": 0,
            "wrapper": {
                "width": "",
                "class": "",
                "id": ""
            },
            "message": "Add a link and the button will auto appear on the frontend only.",
            "new_lines": "wpautop",
            "esc_html": 0
        },
        {
            "key": "field_62d5286250407",
            "label": "Link url",
            "name": "link_url",
            "type": "link",
            "instructions": "",
            "required": 0,
            "conditional_logic": 0,
            "wrapper": {
                "width": "",
                "class": "",
                "id": ""
            },
            "return_format": "url"
        },
        {
            "key": "field_62d52cc050083",
            "label": "<b>Letter of the day<\/b>",
            "name": "",
            "type": "message",
            "instructions": "",
            "required": 0,
            "conditional_logic": 0,
            "wrapper": {
                "width": "",
                "class": "",
                "id": ""
            },
            "message": "Select the letter of the day to feature below.",
            "new_lines": "wpautop",
            "esc_html": 0
        },
        {
            "key": "field_62d52c09089d5",
            "label": "Letter",
            "name": "letter",
            "type": "post_object",
            "instructions": "",
            "required": 0,
            "conditional_logic": 0,
            "wrapper": {
                "width": "",
                "class": "",
                "id": ""
            },
            "post_type": [
                "letter"
            ],
            "taxonomy": "",
            "allow_null": 0,
            "multiple": 0,
            "return_format": "id",
            "ui": 1
        }
    ],
    "location": [
        [
            {
                "param": "block",
                "operator": "==",
                "value": "acf\/letter-of-the-day"
            }
        ]
    ],
    "menu_order": 0,
    "position": "normal",
    "style": "default",
    "label_placement": "top",
    "instruction_placement": "label",
    "hide_on_screen": "",
    "active": true,
    "description": "",
    "show_in_rest": 0,
    "modified": 1658180998
}